sansldap/__init__.py
sansldap/_authentication.py
sansldap/_controls.py
sansldap/_filter.py
sansldap/_messages.py
sansldap/_session.py
sansldap/_version.py
sansldap/asn1.py
sansldap/py.typed
sansldap/schema.py
sansldap-0.1.0.dist-info/LICENSE
sansldap-0.1.0.dist-info/METADATA
sansldap-0.1.0.dist-info/WHEEL
sansldap-0.1.0.dist-info/top_level.txt
sansldap-0.1.0.dist-info/RECORD
